smart_energy_meter_fsm.v
module smart_energy_meter_fsm
#(
    parameter INIT_TICKS = 2,
    parameter LOW_CREDIT_TIMEOUT = 3
)
(
    input  wire clk,
    input  wire rst,
    input  wire sample_tick,
    input  wire overload,
    input  wire tamper_detected,
    input  wire pay_received,
    input  wire low_credit,

    output reg  measure_enable,
    output reg  relay_on,
    output reg  warning,
    output reg  tamper_alarm,
    output reg [2:0] state_dbg
);

    // State encoding
    localparam S_INIT           = 3'd0;
    localparam S_NORMAL         = 3'd1;
    localparam S_LOW_CREDIT     = 3'd2;
    localparam S_DISCONNECTED   = 3'd3;
    localparam S_OVERLOAD_TRIP  = 3'd4;
    localparam S_TAMPER         = 3'd5;

    reg [2:0] state, next_state;

    reg [3:0] init_counter;
    reg [3:0] low_credit_counter;

    //----------------------------------------------------
    // State Register
    //----------------------------------------------------
    always @(posedge clk)
    begin
        if (rst)
            state <= S_INIT;
        else
            state <= next_state;
    end

    //----------------------------------------------------
    // Counters
    //----------------------------------------------------

    always @(posedge clk)
    begin
        if(rst)
            init_counter <= 0;
        else if(state == S_INIT)
        begin
            if(init_counter < INIT_TICKS)
                init_counter <= init_counter + 1;
        end
        else
            init_counter <= 0;
    end

    always @(posedge clk)
    begin
        if(rst)
            low_credit_counter <= 0;

        else if(state == S_LOW_CREDIT)
        begin
            if(low_credit_counter < LOW_CREDIT_TIMEOUT)
                low_credit_counter <= low_credit_counter + 1;
        end
        else
            low_credit_counter <= 0;
    end
    //----------------------------------------------------
    // Next State Logic
    //----------------------------------------------------
    always @(*)
    begin
        next_state = state;

        case(state)

        //------------------------------------------------
        S_INIT:
        begin
            if (init_counter >= INIT_TICKS)
                next_state = S_NORMAL;
        end

        //------------------------------------------------
        S_NORMAL:
        begin
            if (tamper_detected)
                next_state = S_TAMPER;
            else if (overload)
                next_state = S_OVERLOAD_TRIP;
            else if (low_credit)
                next_state = S_LOW_CREDIT;
        end

        //------------------------------------------------
        S_LOW_CREDIT:
        begin
            if (tamper_detected)
                next_state = S_TAMPER;
            else if (overload)
                next_state = S_OVERLOAD_TRIP;
            else if (pay_received)
                next_state = S_NORMAL;
            else if (low_credit_counter >= LOW_CREDIT_TIMEOUT)
                next_state = S_DISCONNECTED;
        end

        //------------------------------------------------
        S_DISCONNECTED:
        begin
            if (tamper_detected)
                next_state = S_TAMPER;
            else if (overload)
                next_state = S_OVERLOAD_TRIP;
            else if (pay_received)
                next_state = S_NORMAL;
        end

        //------------------------------------------------
        S_OVERLOAD_TRIP:
        begin
            if (tamper_detected)
                next_state = S_TAMPER;
            else if (!overload && pay_received)
                next_state = S_NORMAL;
        end

        //------------------------------------------------
        S_TAMPER:
        begin
            if (!tamper_detected && pay_received)
                next_state = S_NORMAL;
        end

        default:
            next_state = S_INIT;

        endcase
    end

    //----------------------------------------------------
    // Output Logic (Moore FSM)
    //----------------------------------------------------
    always @(*)
    begin

        relay_on       = 0;
        warning        = 0;
        tamper_alarm   = 0;
        measure_enable = 0;

        case(state)

        S_INIT:
        begin
        end

        S_NORMAL:
        begin
            relay_on       = 1;
            measure_enable = sample_tick;
        end

        S_LOW_CREDIT:
        begin
            relay_on       = 1;
            warning        = 1;
            measure_enable = sample_tick;
        end

        S_DISCONNECTED:
        begin
        end

        S_OVERLOAD_TRIP:
        begin
            warning = 1;
        end

        S_TAMPER:
        begin
            tamper_alarm = 1;
        end

        endcase

    end

    //----------------------------------------------------
    // Debug State
    //----------------------------------------------------
    always @(*)
    begin
        state_dbg = state;
    end

endmodule

tb_smart_energy_meter_fsm.v
`timescale 1ns/1ps

module smart_energy_meter_fsm_tb;

reg clk;
reg rst;
reg sample_tick;
reg overload;
reg tamper_detected;
reg pay_received;
reg low_credit;

wire measure_enable;
wire relay_on;
wire warning;
wire tamper_alarm;
wire [2:0] state_dbg;

smart_energy_meter_fsm DUT
(
    .clk(clk),
    .rst(rst),
    .sample_tick(sample_tick),
    .overload(overload),
    .tamper_detected(tamper_detected),
    .pay_received(pay_received),
    .low_credit(low_credit),

    .measure_enable(measure_enable),
    .relay_on(relay_on),
    .warning(warning),
    .tamper_alarm(tamper_alarm),
    .state_dbg(state_dbg)
);

//////////////////////////////////////////////////////////
// Clock Generation
//////////////////////////////////////////////////////////
initial
begin
    clk = 0;
    forever #5 clk = ~clk;
end

//////////////////////////////////////////////////////////
// VCD Dump
//////////////////////////////////////////////////////////
initial
begin
    $dumpfile("wave_smart_energy_meter_fsm.vcd");
    $dumpvars(0, smart_energy_meter_fsm_tb);
end

//////////////////////////////////////////////////////////
// Stimulus
//////////////////////////////////////////////////////////
initial
begin

    rst             = 1;
    sample_tick     = 0;
    overload        = 0;
    tamper_detected = 0;
    pay_received    = 0;
    low_credit      = 0;

    //--------------------------------------------------
    // Reset
    //--------------------------------------------------
    #20;
    rst = 0;

    //--------------------------------------------------
    // Wait for INIT -> NORMAL
    //--------------------------------------------------
    #40;

    //--------------------------------------------------
    // Sample Tick Check
    //--------------------------------------------------
    sample_tick = 1;
    #10;
    sample_tick = 0;

    #20;

    //--------------------------------------------------
    // LOW CREDIT Scenario
    //--------------------------------------------------
    low_credit = 1;
    #50;

    //--------------------------------------------------
    // Payment Restore
    //--------------------------------------------------
    pay_received = 1;
    #10;
    pay_received = 0;
    low_credit   = 0;

    #30;

    //--------------------------------------------------
    // LOW CREDIT -> DISCONNECTED
    //--------------------------------------------------
    low_credit = 1;

    #80;

    low_credit = 0;

    //--------------------------------------------------
    // Restore from DISCONNECTED
    //--------------------------------------------------
    pay_received = 1;
    #10;
    pay_received = 0;

    #30;

    //--------------------------------------------------
    // OVERLOAD TRIP
    //--------------------------------------------------
    overload = 1;

    #30;

    overload     = 0;
    pay_received = 1;

    #10;

    pay_received = 0;

    #30;

    //--------------------------------------------------
    // TAMPER
    //--------------------------------------------------
    tamper_detected = 1;

    #30;

    tamper_detected = 0;
    pay_received    = 1;

    #10;

    pay_received = 0;

    #40;

    $finish;

end

endmodule

wave_smart_energy_meter_fsm.vcd
$date
	Mon Jun 22 09:33:17 2026
$end
$version
	Icarus Verilog
$end
$timescale
	1ps
$end
$scope module smart_energy_meter_fsm_tb $end
$var wire 1 ! warning $end
$var wire 1 " tamper_alarm $end
$var wire 3 # state_dbg [2:0] $end
$var wire 1 $ relay_on $end
$var wire 1 % measure_enable $end
$var reg 1 & clk $end
$var reg 1 ' low_credit $end
$var reg 1 ( overload $end
$var reg 1 ) pay_received $end
$var reg 1 * rst $end
$var reg 1 + sample_tick $end
$var reg 1 , tamper_detected $end
$scope module DUT $end
$var wire 1 & clk $end
$var wire 1 ' low_credit $end
$var wire 1 ( overload $end
$var wire 1 ) pay_received $end
$var wire 1 * rst $end
$var wire 1 + sample_tick $end
$var wire 1 , tamper_detected $end
$var parameter 32 - INIT_TICKS $end
$var parameter 32 . LOW_CREDIT_TIMEOUT $end
$var parameter 3 / S_DISCONNECTED $end
$var parameter 3 0 S_INIT $end
$var parameter 3 1 S_LOW_CREDIT $end
$var parameter 3 2 S_NORMAL $end
$var parameter 3 3 S_OVERLOAD_TRIP $end
$var parameter 3 4 S_TAMPER $end
$var reg 4 5 init_counter [3:0] $end
$var reg 4 6 low_credit_counter [3:0] $end
$var reg 1 % measure_enable $end
$var reg 3 7 next_state [2:0] $end
$var reg 1 $ relay_on $end
$var reg 3 8 state [2:0] $end
$var reg 3 9 state_dbg [2:0] $end
$var reg 1 " tamper_alarm $end
$var reg 1 ! warning $end
$upscope $end
$upscope $end
$enddefinitions $end
$comment Show the parameter values. $end
$dumpall
b101 4
b100 3
b1 2
b10 1
b0 0
b11 /
b11 .
b10 -
$end
#0
$dumpvars
bx 9
bx 8
b0 7
bx 6
bx 5
0,
0+
1*
0)
0(
0'
0&
0%
0$
bx #
0"
0!
$end
#5000
b0 #
b0 9
b0 8
b0 5
b0 6
1&
#10000
0&
#15000
1&
#20000
0&
0*
#25000
b1 5
1&
#30000
0&
#35000
b1 7
b10 5
1&
#40000
0&
#45000
b1 #
b1 9
1$
b1 8
1&
#50000
0&
#55000
b0 5
1&
#60000
1%
1$
0&
1+
#65000
1&
#70000
0%
1$
0&
0+
#75000
1&
#80000
0&
#85000
1&
#90000
b10 7
0&
1'
#95000
b10 #
b10 9
1!
1$
b10 8
1&
#100000
0&
#105000
b1 6
1&
#110000
0&
#115000
b10 6
1&
#120000
0&
#125000
b11 7
b11 6
1&
#130000
0&
#135000
b11 #
b11 9
0!
0$
b11 8
1&
#140000
b1 7
0&
1)
#145000
b1 #
b1 9
1$
b10 7
b1 8
b0 6
1&
#150000
b1 7
0&
0'
0)
#155000
1&
#160000
0&
#165000
1&
#170000
0&
#175000
1&
#180000
b10 7
0&
1'
#185000
b10 #
b10 9
1!
1$
b10 8
1&
#190000
0&
#195000
b1 6
1&
#200000
0&
#205000
b10 6
1&
#210000
0&
#215000
b11 7
b11 6
1&
#220000
0&
#225000
b11 #
b11 9
0!
0$
b11 8
1&
#230000
0&
#235000
b0 6
1&
#240000
0&
#245000
1&
#250000
0&
#255000
1&
#260000
b1 7
0&
1)
0'
#265000
b1 #
b1 9
1$
b1 8
1&
#270000
0&
0)
#275000
1&
#280000
0&
#285000
1&
#290000
0&
#295000
1&
#300000
b100 7
0&
1(
#305000
b100 #
b100 9
1!
0$
b100 8
1&
#310000
0&
#315000
1&
#320000
0&
#325000
1&
#330000
b1 7
0&
1)
0(
#335000
b1 #
b1 9
1$
0!
b1 8
1&
#340000
0&
0)
#345000
1&
#350000
0&
#355000
1&
#360000
0&
#365000
1&
#370000
b101 7
0&
1,
#375000
b101 #
b101 9
1"
0$
b101 8
1&
#380000
0&
#385000
1&
#390000
0&
#395000
1&
#400000
b1 7
0&
1)
0,
#405000
b1 #
b1 9
1$
0"
b1 8
1&
#410000
0&
0)
