smart_meter.sv
module smart_energy_meter_fsm #(
    parameter INIT_TICKS = 2,
    parameter LOW_CREDIT_TIMEOUT = 3
)
(
    input  clk,
    input  rst,
    input  sample_tick,
    input  overload,
    input  tamper_detected,
    input  pay_received,
    input  low_credit,

    output reg measure_enable,
    output reg relay_on,
    output reg warning,
    output reg tamper_alarm,
    output reg [2:0] state_dbg
);

 
    parameter S_INIT          = 3'b000;
    parameter S_NORMAL        = 3'b001;
    parameter S_LOW_CREDIT    = 3'b010;
    parameter S_DISCONNECTED  = 3'b011;
    parameter S_OVERLOAD_TRIP = 3'b100;
    parameter S_TAMPER        = 3'b101;

    reg [2:0] state, next_state;


    reg [3:0] timer;

  
    always @(posedge clk) begin
        if (rst)
            state <= S_INIT;
        else
            state <= next_state;
    end


    always @(posedge clk) begin
        if (rst)
            timer <= 0;

        else begin

            case(state)

                S_INIT:
                    if (timer < INIT_TICKS)
                        timer <= timer + 1;
                    else
                        timer <= 0;

                S_LOW_CREDIT:
                    if (timer < LOW_CREDIT_TIMEOUT)
                        timer <= timer + 1;
                    else
                        timer <= 0;

                default:
                    timer <= 0;

            endcase

        end
    end

    always @(*) begin

        next_state = state;

        case(state)


            S_INIT: begin
                if (timer >= INIT_TICKS)
                    next_state = S_NORMAL;
            end


            S_NORMAL: begin
		    if (tamper_detected)
                    next_state = S_TAMPER;
                else if (overload)
                    next_state = S_OVERLOAD_TRIP;

                else if (low_credit)
                    next_state = S_LOW_CREDIT;

            end

            S_LOW_CREDIT: begin

                if (tamper_detected)
                    next_state = S_TAMPER;

                else if (overload)
                    next_state = S_OVERLOAD_TRIP;

                else if (pay_received)
                    next_state = S_NORMAL;

                else if (timer >= LOW_CREDIT_TIMEOUT)
                    next_state = S_DISCONNECTED;

            end

            S_DISCONNECTED: begin
                if (pay_received)
                    next_state = S_NORMAL;
            end

            S_OVERLOAD_TRIP: begin
                if (!overload && pay_received)
                    next_state = S_NORMAL;
            end

            S_TAMPER: begin
                if (!tamper_detected && pay_received)
                    next_state = S_NORMAL;
            end

            default:
                next_state = S_INIT;

        endcase

    end

    always @(*) begin

        relay_on       = 0;
        measure_enable = 0;
        warning        = 0;
        tamper_alarm   = 0;

        case(state)

            S_NORMAL: begin
                relay_on       = 1;
                measure_enable = sample_tick;
            end

            S_LOW_CREDIT: begin
                relay_on       = 1;
                warning        = 1;
                measure_enable = sample_tick;
            end

            S_OVERLOAD_TRIP: begin
                warning = 1;
            end

            S_TAMPER: begin
                tamper_alarm = 1;
            end

        endcase

    end

    always @(*) begin
        state_dbg = state;
    end

endmodule

smart_meter_tb.sv
`timescale 1ns/1ps

module tb_smart_energy_meter_fsm;

    reg clk;
    reg rst;
    reg sample_tick;
    reg overload;
    reg tamper_detected;
    reg pay_received;
    reg low_credit;

    wire measure_enable;
    wire relay_on;
    wire warning;
    wire tamper_alarm;
    wire [2:0] state_dbg;

    smart_energy_meter_fsm #(
        .INIT_TICKS(2),
        .LOW_CREDIT_TIMEOUT(3)
    ) DUT (
        .clk(clk),
        .rst(rst),
        .sample_tick(sample_tick),
        .overload(overload),
        .tamper_detected(tamper_detected),
        .pay_received(pay_received),
        .low_credit(low_credit),

        .measure_enable(measure_enable),
        .relay_on(relay_on),
        .warning(warning),
        .tamper_alarm(tamper_alarm),
        .state_dbg(state_dbg)
    );

    initial begin
        clk = 0;
        forever #5 clk = ~clk;   // 10ns clock period
    end

    initial begin
        $dumpfile("wave_smart_energy_meter_fsm.vcd");
        $dumpvars(0, tb_smart_energy_meter_fsm);
    end

    initial begin
        rst = 1;
        sample_tick = 0;
        overload = 0;
        tamper_detected = 0;
        pay_received = 0;
        low_credit = 0;

        #20;
        rst = 0;

        #40;

        if(state_dbg == 3'b001)
            $display("PASS : INIT -> NORMAL");
        else
            $display("FAIL : INIT -> NORMAL");

        sample_tick = 1;
        #10;

        if(measure_enable)
            $display("PASS : Measurement Enabled");
        else
            $display("FAIL : Measurement Enabled");

        sample_tick = 0;
        #10;

        low_credit = 1;
        #10;

        if(warning)
            $display("PASS : Low Credit Warning");
        else
            $display("FAIL : Low Credit Warning");

        low_credit = 0;
        #50;

        if(state_dbg == 3'b011)
            $display("PASS : Disconnected after timeout");
        else
            $display("FAIL : Disconnect failed");

        pay_received = 1;
        #10;
        pay_received = 0;
        #20;

        if(state_dbg == 3'b001)
            $display("PASS : Payment Restoration");
        else
            $display("FAIL : Payment Restoration");

        overload = 1;
        #10;

        if(state_dbg == 3'b100)
            $display("PASS : Overload Trip");
        else
            $display("FAIL : Overload Trip");

        overload = 0;
        pay_received = 1;
        #10;

        pay_received = 0;
        #20;

        if(state_dbg == 3'b001)
            $display("PASS : Overload Recovery");
        else
            $display("FAIL : Overload Recovery");

        tamper_detected = 1;
        #10;

        if(state_dbg == 3'b101)
            $display("PASS : Tamper Detected");
        else
            $display("FAIL : Tamper Detection");

        tamper_detected = 0;
        pay_received = 1;
        #10;

        pay_received = 0;
        #20;

        if(state_dbg == 3'b001)
            $display("PASS : Tamper Recovery");
        else
            $display("FAIL : Tamper Recovery");

        tamper_detected = 1;
        overload = 1;
        low_credit = 1;

        #10;

        if(state_dbg == 3'b101)
            $display("PASS : Priority Correct (Tamper Highest)");
        else
            $display("FAIL : Priority Error");

        #20;
        $display("\nSUMMARY : smart_energy_meter_fsm PASS\n");
        $finish;

    end

endmodule

wave_smart_energy_meter_fsm.vcd
$date
	Mon Jun 15 09:57:06 2026
$end
$version
	Icarus Verilog
$end
$timescale
	1ps
$end
$scope module tb_smart_energy_meter_fsm $end
$var wire 1 ! warning $end
$var wire 1 " tamper_alarm $end
$var wire 3 # state_dbg [2:0] $end
$var wire 1 $ relay_on $end
$var wire 1 % measure_enable $end
$var reg 1 & clk $end
$var reg 1 ' low_credit $end
$var reg 1 ( overload $end
$var reg 1 ) pay_received $end
$var reg 1 * rst $end
$var reg 1 + sample_tick $end
$var reg 1 , tamper_detected $end
$scope module DUT $end
$var wire 1 & clk $end
$var wire 1 ' low_credit $end
$var wire 1 ( overload $end
$var wire 1 ) pay_received $end
$var wire 1 * rst $end
$var wire 1 + sample_tick $end
$var wire 1 , tamper_detected $end
$var reg 1 % measure_enable $end
$var reg 3 - next_state [2:0] $end
$var reg 1 $ relay_on $end
$var reg 3 . state [2:0] $end
$var reg 3 / state_dbg [2:0] $end
$var reg 1 " tamper_alarm $end
$var reg 4 0 timer [3:0] $end
$var reg 1 ! warning $end
$upscope $end
$upscope $end
$enddefinitions $end
#0
$dumpvars
bx 0
bx /
bx .
b0 -
0,
0+
1*
0)
0(
0'
0&
0%
0$
bx #
0"
0!
$end
#5000
b0 #
b0 /
b0 .
b0 0
1&
#10000
0&
#15000
1&
#20000
0&
0*
#25000
b1 0
1&
#30000
0&
#35000
b1 -
b10 0
1&
#40000
0&
#45000
b1 #
b1 /
1$
b1 .
b0 0
1&
#50000
0&
#55000
1&
#60000
1%
1$
0&
1+
#65000
1&
#70000
0%
1$
0&
0+
#75000
1&
#80000
b10 -
0&
1'
#85000
b10 #
b10 /
1!
1$
b10 .
1&
#90000
0&
0'
#95000
b1 0
1&
#100000
0&
#105000
b10 0
1&
#110000
0&
#115000
b11 -
b11 0
1&
#120000
0&
#125000
b11 #
b11 /
0!
0$
b11 .
b0 0
1&
#130000
0&
#135000
1&
#140000
b1 -
0&
1)
#145000
b1 #
b1 /
1$
b1 .
1&
#150000
0&
0)
#155000
1&
#160000
0&
#165000
1&
#170000
b100 -
0&
1(
#175000
b100 #
b100 /
1!
0$
b100 .
1&
#180000
b1 -
0&
1)
0(
#185000
b1 #
b1 /
1$
0!
b1 .
1&
#190000
0&
0)
#195000
1&
#200000
0&
#205000
1&
#210000
b101 -
0&
1,
#215000
b101 #
b101 /
1"
0$
b101 .
1&
#220000
b1 -
0&
1)
0,
#225000
b1 #
b1 /
1$
0"
b1 .
1&
#230000
0&
0)
#235000
1&
#240000
0&
#245000
1&
#250000
b101 -
0&
1'
1(
1,
#255000
b101 #
b101 /
1"
0$
b101 .
1&
